[
  {
    "name": "Stonework",
    "era": 1,
    "type": "Defense",
    "unlocks": [
      "District: Keep"
    ],
    "effects": [
      "+100 Fortification on Capital"
    ],
    "prereq": "",
    "faction": [
      "Aspect",
      "Kin",
      "Lost Lords",
      "Necrophage",
      "Tahuk"
    ],
    "excludes": "",
    "coords": {
      "xPct": 21.3,
      "yPct": 29.76
    }
  },
  {
    "name": "Voice of the Masses",
    "era": 1,
    "type": "Society",
    "unlocks": [
      "District: Forum"
    ],
    "effects": [
      "+1 Scribe slot on Capital"
    ],
    "prereq": "",
    "faction": [
      "Aspect",
      "Kin",
      "Lost Lords",
      "Necrophage",
      "Tahuk"
    ],
    "excludes": "",
    "coords": {
      "xPct": 35.57,
      "yPct": 7.25
    }
  },
  {
    "name": "Civil Order",
    "era": 1,
    "type": "Society",
    "unlocks": [
      "Improvement: Traveler's Shrine"
    ],
    "effects": [
      "+12 Approval on Capital"
    ],
    "prereq": "",
    "faction": [
      "Aspect",
      "Kin",
      "Lost Lords",
      "Necrophage",
      "Tahuk"
    ],
    "excludes": "",
    "coords": {
      "xPct": 47.4,
      "yPct": 16.96
    }
  },
  {
    "name": "Fencing",
    "era": 1,
    "type": "Society",
    "unlocks": [
      "District: Farm"
    ],
    "effects": [
      "+1 Citizen Slot on Capital",
      "+1 Artisan Slot on Capital"
    ],
    "prereq": "",
    "faction": [
      "Aspect",
      "Kin",
      "Lost Lords",
      "Necrophage",
      "Tahuk"
    ],
    "excludes": "",
    "coords": {
      "xPct": 59.22,
      "yPct": 7.25
    }
  },
  {
    "name": "Workshop",
    "era": 1,
    "type": "Economy",
    "unlocks": [
      "District: Works",
      "Action: Remove Forest"
    ],
    "effects": [],
    "prereq": "",
    "faction": [
      "Aspect",
      "Kin",
      "Lost Lords",
      "Necrophage",
      "Tahuk"
    ],
    "excludes": "",
    "coords": {
      "xPct": 71.09,
      "yPct": 29.82
    }
  },
  {
    "name": "Currency",
    "era": 1,
    "type": "Economy",
    "unlocks": [
      "District: Merchant's House"
    ],
    "effects": [
      "+8 Dust on Capital"
    ],
    "prereq": "",
    "faction": [
      "Aspect",
      "Kin",
      "Lost Lords",
      "Necrophage",
      "Tahuk"
    ],
    "excludes": "",
    "coords": {
      "xPct": 71.04,
      "yPct": 58.0
    }
  },
  {
    "name": "Keystones",
    "era": 1,
    "type": "Discovery",
    "unlocks": [
      "District: Bridge",
      "Action: Build Dam"
    ],
    "effects": [],
    "prereq": "",
    "faction": [
      "Aspect",
      "Kin",
      "Lost Lords",
      "Necrophage",
      "Tahuk"
    ],
    "excludes": "",
    "coords": {
      "xPct": 56.88,
      "yPct": 73.96
    }
  },
  {
    "name": "Scientific Charter",
    "era": 1,
    "type": "Discovery",
    "unlocks": [
      "District: Laboratory",
      "Improves the rewards from Curiosities"
    ],
    "effects": [],
    "prereq": "",
    "faction": [
      "Aspect",
      "Kin",
      "Lost Lords",
      "Necrophage",
      "Tahuk"
    ],
    "excludes": "",
    "coords": {
      "xPct": 37.92,
      "yPct": 74.06
    }
  },
  {
    "name": "The Strength of Garin",
    "era": 1,
    "type": "Defense",
    "unlocks": [],
    "effects": [
      "+5 Defense on Units",
      "+2 Industry on Military Districts"
    ],
    "prereq": "",
    "faction": [
      "Kin"
    ],
    "excludes": "",
    "coords": {
      "xPct": 30.78,
      "yPct": 42.0
    }
  },
  {
    "name": "Scavenging",
    "era": 1,
    "type": "Defense",
    "unlocks": [],
    "effects": [
      "+25% gains on Battle Spoils",
      "+15 Health on non-Hero",
      "+5 Damage on non-Hero"
    ],
    "prereq": "",
    "faction": [
      "Aspect",
      "Kin",
      "Lost Lords",
      "Necrophage",
      "Tahuk"
    ],
    "excludes": "",
    "coords": {
      "xPct": 21.3,
      "yPct": 58.0
    }
  },
  {
    "name": "Shock Tactics",
    "era": 2,
    "type": "Defense",
    "unlocks": [
      "Improvement: Garrison"
    ],
    "effects": [
      "+200 District Fortification on City Hall",
      "+200 District Fortification on Ministry"
    ],
    "prereq": "",
    "faction": [
      "Aspect",
      "Kin",
      "Lost Lords",
      "Necrophage",
      "Tahuk"
    ],
    "excludes": "",
    "coords": {
      "xPct": 21.3,
      "yPct": 29.76
    }
  },
  {
    "name": "The Hand of Garin",
    "era": 2,
    "type": "Defense",
    "unlocks": [
      "Improvement: Legion Vaults",
      "Unit Specialization: Architect"
    ],
    "effects": [],
    "prereq": "",
    "faction": [
      "Kin"
    ],
    "excludes": "",
    "coords": {
      "xPct": 30.78,
      "yPct": 42.0
    }
  },
  {
    "name": "Sheredyn's Creed",
    "era": 2,
    "type": "Defense",
    "unlocks": [
      "Unit Specialization: Explorer",
      "Unit Specialization: Harrier",
      "Unit Specialization: Warden"
    ],
    "effects": [],
    "prereq": "",
    "faction": [
      "Aspect",
      "Kin",
      "Lost Lords",
      "Necrophage",
      "Tahuk"
    ],
    "excludes": "",
    "coords": {
      "xPct": 21.3,
      "yPct": 58.0
    }
  },
  {
    "name": "Foreign Affairs",
    "era": 2,
    "type": "Society",
    "unlocks": [
      "Protectorate Slot: 1"
    ],
    "effects": [
      "-25% Dust cost for Bribe action"
    ],
    "prereq": "",
    "faction": [
      "Aspect",
      "Kin",
      "Lost Lords",
      "Necrophage",
      "Tahuk"
    ],
    "excludes": "",
    "coords": {
      "xPct": 28.45,
      "yPct": 4.3
    }
  },
  {
    "name": "Common Rights",
    "era": 2,
    "type": "Society",
    "unlocks": [
      "Improvement: Scriptorium"
    ],
    "effects": [
      "+4 Influence income on Capital"
    ],
    "prereq": "",
    "faction": [
      "Aspect",
      "Kin",
      "Lost Lords",
      "Necrophage",
      "Tahuk"
    ],
    "excludes": "",
    "coords": {
      "xPct": 40.28,
      "yPct": 23.42
    }
  },
  {
    "name": "Creed",
    "era": 2,
    "type": "Society",
    "unlocks": [
      "Improvement: Lodgings",
      "Improvement: Emergency Dwellings"
    ],
    "effects": [],
    "prereq": "",
    "faction": [
      "Aspect",
      "Kin",
      "Lost Lords",
      "Necrophage",
      "Tahuk"
    ],
    "excludes": "",
    "coords": {
      "xPct": 47.41,
      "yPct": 10.64
    }
  },
  {
    "name": "Seedbank",
    "era": 2,
    "type": "Society",
    "unlocks": [
      "Improvement: Laborer's Hut",
      "Improvement: Granary",
      "Converter: Toil in the Fields"
    ],
    "effects": [],
    "prereq": "",
    "faction": [
      "Aspect",
      "Kin",
      "Lost Lords",
      "Necrophage",
      "Tahuk"
    ],
    "excludes": "",
    "coords": {
      "xPct": 54.5,
      "yPct": 23.42
    }
  },
  {
    "name": "Diplomat's Manse",
    "era": 2,
    "type": "Society",
    "unlocks": [
      "Treaty: Immigration Policy",
      "Treaty: Win-Win Relations"
    ],
    "effects": [
      "+100 Influence"
    ],
    "prereq": "",
    "faction": [
      "Aspect",
      "Kin",
      "Lost Lords",
      "Necrophage",
      "Tahuk"
    ],
    "excludes": "",
    "coords": {
      "xPct": 66.32,
      "yPct": 4.3
    }
  },
  {
    "name": "Markets",
    "era": 2,
    "type": "Economy",
    "unlocks": [
      "District: Trading Post",
      "Traders' Trails: Dirt Roads"
    ],
    "effects": [
      "1 Movement Points max to cross a road Tile"
    ],
    "prereq": "",
    "faction": [
      "Aspect",
      "Kin",
      "Lost Lords",
      "Necrophage",
      "Tahuk"
    ],
    "excludes": "",
    "coords": {
      "xPct": 63.97,
      "yPct": 42.42
    }
  },
  {
    "name": "Collective Will",
    "era": 2,
    "type": "Economy",
    "unlocks": [
      "Improvement: Blast Furnace"
    ],
    "effects": [
      "+4 Food on Capital",
      "+4 Industry on Capital"
    ],
    "prereq": "",
    "faction": [
      "Aspect",
      "Kin",
      "Lost Lords",
      "Necrophage",
      "Tahuk"
    ],
    "excludes": "",
    "coords": {
      "xPct": 73.4,
      "yPct": 29.75
    }
  },
  {
    "name": "Dustlytics",
    "era": 2,
    "type": "Economy",
    "unlocks": [
      "Improvement: Lithosphere Gallery"
    ],
    "effects": [
      "+6 Dust on City Hall",
      "+4 Dust on Ministry"
    ],
    "prereq": "",
    "faction": [
      "Aspect",
      "Kin",
      "Lost Lords",
      "Necrophage",
      "Tahuk"
    ],
    "excludes": "",
    "coords": {
      "xPct": 73.4,
      "yPct": 58.3
    }
  },
  {
    "name": "Materials Science",
    "era": 2,
    "type": "Discovery",
    "unlocks": [
      "Improvement: Geodesic Dome",
      "Improvement: Beacon of Science"
    ],
    "effects": [
      "+4 Science on Capital"
    ],
    "prereq": "",
    "faction": [
      "Aspect",
      "Kin",
      "Lost Lords",
      "Necrophage",
      "Tahuk"
    ],
    "excludes": "",
    "coords": {
      "xPct": 40.28,
      "yPct": 64.64
    }
  },
  {
    "name": "Geology",
    "era": 2,
    "type": "Discovery",
    "unlocks": [
      "Landscape Action: Rewild (restores Barren Tiles)"
    ],
    "effects": [
      "-25% Influence cost for Found Camp (Works for Necromancer and Aspects too)"
    ],
    "prereq": "",
    "faction": [
      "Aspect",
      "Kin",
      "Lost Lords",
      "Necrophage",
      "Tahuk"
    ],
    "excludes": "",
    "coords": {
      "xPct": 47.41,
      "yPct": 77.3
    }
  },
  {
    "name": "Hydromatic Laboratory",
    "era": 2,
    "type": "Discovery",
    "unlocks": [
      "Improvement: Hydropump"
    ],
    "effects": [
      "+25% Precision for season predictability"
    ],
    "prereq": "Keystones",
    "faction": [
      "Aspect",
      "Kin",
      "Lost Lords",
      "Necrophage",
      "Tahuk"
    ],
    "excludes": "",
    "coords": {
      "xPct": 54.5,
      "yPct": 64.64
    }
  },
  {
    "name": "Conscription",
    "era": 3,
    "type": "Defense",
    "unlocks": [
      "Improvement: Military Efficiency",
      "Converter: Propaganda Machine"
    ],
    "effects": [
      "+50 District Fortification on Military Districts"
    ],
    "prereq": "",
    "faction": [
      "Aspect",
      "Kin",
      "Lost Lords",
      "Necrophage",
      "Tahuk"
    ],
    "excludes": "",
    "coords": {
      "xPct": 21.32,
      "yPct": 26.42
    }
  },
  {
    "name": "The Wisdom of Garin",
    "era": 3,
    "type": "Defense",
    "unlocks": [
      "Improvement: Legionaries Workshop"
    ],
    "effects": [
      "-25% Industry cost on Military-related Improvements"
    ],
    "prereq": "",
    "faction": [
      "Kin"
    ],
    "excludes": "",
    "coords": {
      "xPct": 30.78,
      "yPct": 42.0
    }
  },
  {
    "name": "Composite Materials",
    "era": 3,
    "type": "Defense",
    "unlocks": [
      "Unit Specialization: Heavy Archer",
      "Unit Specialization: Bloodletter",
      "Unit Specialization: Clarion",
      "Unit Specialization: Protector"
    ],
    "effects": [],
    "prereq": "",
    "faction": [
      "Kin"
    ],
    "excludes": "",
    "coords": {
      "xPct": 21.32,
      "yPct": 64.53
    }
  },
  {
    "name": "Statecraft",
    "era": 3,
    "type": "Society",
    "unlocks": [
      "Protectorate Slot: 1",
      "Unit Specialization: Minor Factions Tier 1"
    ],
    "effects": [],
    "prereq": "",
    "faction": [
      "Aspect",
      "Kin",
      "Lost Lords",
      "Necrophage",
      "Tahuk"
    ],
    "excludes": "",
    "coords": {
      "xPct": 28.45,
      "yPct": 4.3
    }
  },
  {
    "name": "Citizenship",
    "era": 3,
    "type": "Society",
    "unlocks": [
      "Improvement: Halls of Power"
    ],
    "effects": [
      "+2 Influence on City Hall",
      "+1 Influence on Ministry"
    ],
    "prereq": "",
    "faction": [
      "Aspect",
      "Kin",
      "Lost Lords",
      "Necrophage",
      "Tahuk"
    ],
    "excludes": "",
    "coords": {
      "xPct": 40.28,
      "yPct": 23.42
    }
  },
  {
    "name": "Urban Planning",
    "era": 3,
    "type": "Society",
    "unlocks": [
      "Improvement: Citizen's Center"
    ],
    "effects": [
      "+4 Food on City Hall",
      "+2 Food on Ministry"
    ],
    "prereq": "",
    "faction": [
      "Aspect",
      "Kin",
      "Lost Lords",
      "Necrophage",
      "Tahuk"
    ],
    "excludes": "",
    "coords": {
      "xPct": 47.41,
      "yPct": 10.64
    }
  },
  {
    "name": "Hydrology",
    "era": 3,
    "type": "Society",
    "unlocks": [
      "Improvement: Irrigation Channels",
      "Improvement: Wood Ash Pit"
    ],
    "effects": [
      "+2 Food on Farm Districts"
    ],
    "prereq": "",
    "faction": [
      "Aspect",
      "Kin",
      "Lost Lords",
      "Necrophage",
      "Tahuk"
    ],
    "excludes": "",
    "coords": {
      "xPct": 54.5,
      "yPct": 23.42
    }
  },
  {
    "name": "Embassy",
    "era": 3,
    "type": "Society",
    "unlocks": [
      "Treaty: Deeper Collaboration",
      "Treaty: Vision Exchange",
      "Treaty: Join Military"
    ],
    "effects": [],
    "prereq": "",
    "faction": [
      "Aspect",
      "Kin",
      "Lost Lords",
      "Necrophage",
      "Tahuk"
    ],
    "excludes": "",
    "coords": {
      "xPct": 66.32,
      "yPct": 4.3
    }
  },
  {
    "name": "Pyrometallurgy",
    "era": 3,
    "type": "Economy",
    "unlocks": [
      "Improvement: Spire of Industry",
      "Improvement: Corkscrew Drill"
    ],
    "effects": [],
    "prereq": "",
    "faction": [
      "Aspect",
      "Kin",
      "Lost Lords",
      "Necrophage",
      "Tahuk"
    ],
    "excludes": "",
    "coords": {
      "xPct": 63.92,
      "yPct": 32.75
    }
  },
  {
    "name": "Commerce",
    "era": 3,
    "type": "Economy",
    "unlocks": [
      "Improvement: Alchemists' Commission",
      "Improvement: Caravanserai",
      "Traders' Trails: Graded Roads"
    ],
    "effects": [
      "0.5 Movement Points max to cross a road Tile"
    ],
    "prereq": "",
    "faction": [
      "Aspect",
      "Kin",
      "Lost Lords",
      "Necrophage",
      "Tahuk"
    ],
    "excludes": "",
    "coords": {
      "xPct": 63.92,
      "yPct": 54.97
    }
  },
  {
    "name": "Arboreal Insights",
    "era": 3,
    "type": "Economy",
    "unlocks": [
      "Improvement: Lumber Yard",
      "Action: Reforest"
    ],
    "effects": [
      "+2 Industry on Works Districts"
    ],
    "prereq": "",
    "faction": [
      "Aspect",
      "Kin",
      "Lost Lords",
      "Necrophage",
      "Tahuk"
    ],
    "excludes": "",
    "coords": {
      "xPct": 73.4,
      "yPct": 26.42
    }
  },
  {
    "name": "Dustnomics",
    "era": 3,
    "type": "Economy",
    "unlocks": [
      "Improvement: Dust Blasting",
      "Converter: Investors' Graft"
    ],
    "effects": [
      "+4 Dust on Merchant's House Districts"
    ],
    "prereq": "",
    "faction": [
      "Aspect",
      "Kin",
      "Lost Lords",
      "Necrophage",
      "Tahuk"
    ],
    "excludes": "",
    "coords": {
      "xPct": 73.4,
      "yPct": 64.53
    }
  },
  {
    "name": "Research Grants",
    "era": 3,
    "type": "Discovery",
    "unlocks": [
      "Improvement: Research Station",
      "Improvement: Wildlife Lookout"
    ],
    "effects": [
      "+4 Science on City Hall",
      "+2 Science on Ministry"
    ],
    "prereq": "",
    "faction": [
      "Aspect",
      "Kin",
      "Lost Lords",
      "Necrophage",
      "Tahuk"
    ],
    "excludes": "",
    "coords": {
      "xPct": 40.28,
      "yPct": 70.86
    }
  },
  {
    "name": "Collective Sacrifice",
    "era": 3,
    "type": "Discovery",
    "unlocks": [
      "Action: Bait Doomwraith",
      "Action: Close Rift"
    ],
    "effects": [
      "+8 Damage on non-Hero"
    ],
    "prereq": "",
    "faction": [
      "Aspect",
      "Kin",
      "Lost Lords",
      "Necrophage",
      "Tahuk"
    ],
    "excludes": "",
    "coords": {
      "xPct": 54.44,
      "yPct": 70.86
    }
  },
  {
    "name": "Auxiliary Forces",
    "era": 4,
    "type": "Defense",
    "unlocks": [
      "Improvement: Commanders' Table"
    ],
    "effects": [
      "+5 Approval on Improvement"
    ],
    "prereq": "",
    "faction": [
      "Aspect",
      "Kin",
      "Lost Lords",
      "Necrophage",
      "Tahuk"
    ],
    "excludes": "Logistics",
    "coords": {
      "xPct": 16.63,
      "yPct": 26.64
    }
  },
  {
    "name": "Logistics",
    "era": 4,
    "type": "Defense",
    "unlocks": [
      "Improvement: Watchman's Bell"
    ],
    "effects": [
      "-25% Industry on Keep"
    ],
    "prereq": "",
    "faction": [
      "Aspect",
      "Kin",
      "Lost Lords",
      "Necrophage",
      "Tahuk"
    ],
    "excludes": "Auxiliary Forces",
    "coords": {
      "xPct": 26.09,
      "yPct": 26.64
    }
  },
  {
    "name": "The Gaze of Garin",
    "era": 4,
    "type": "Defense",
    "unlocks": [
      "Improvement: Martial Discipline",
      "Unit Specialization: Greatsword"
    ],
    "effects": [],
    "prereq": "",
    "faction": [
      "Kin"
    ],
    "excludes": "",
    "coords": {
      "xPct": 30.78,
      "yPct": 42.0
    }
  },
  {
    "name": "Zelevas' Stamina",
    "era": 4,
    "type": "Defense",
    "unlocks": [
      "Unit Specialization: Pathfinder",
      "Unit Specialization: Harasser",
      "Unit Specialization: Guardian",
      "Unit Specialization: Custodian"
    ],
    "effects": [],
    "prereq": "",
    "faction": [
      "Kin"
    ],
    "excludes": "",
    "coords": {
      "xPct": 21.32,
      "yPct": 61.42
    }
  },
  {
    "name": "Public Works",
    "era": 4,
    "type": "Society",
    "unlocks": [
      "Improvement: Museum"
    ],
    "effects": [
      "+3 Influence on Improvement"
    ],
    "prereq": "",
    "faction": [
      "Aspect",
      "Kin",
      "Lost Lords",
      "Necrophage",
      "Tahuk"
    ],
    "excludes": "Dramatic Arts",
    "coords": {
      "xPct": 28.45,
      "yPct": 4.42
    }
  },
  {
    "name": "Dramatic Arts",
    "era": 4,
    "type": "Society",
    "unlocks": [
      "Improvement: Parade Stands"
    ],
    "effects": [
      "-25% Industry cost on Forum"
    ],
    "prereq": "",
    "faction": [
      "Aspect",
      "Kin",
      "Lost Lords",
      "Necrophage",
      "Tahuk"
    ],
    "excludes": "Public Works",
    "coords": {
      "xPct": 37.9,
      "yPct": 4.42
    }
  },
  {
    "name": "Dignitary Goodwill",
    "era": 4,
    "type": "Society",
    "unlocks": [
      "Protectorate Slot: 1",
      "Unit Specialization: Minor Factions Tier 2"
    ],
    "effects": [],
    "prereq": "",
    "faction": [
      "Aspect",
      "Kin",
      "Lost Lords",
      "Necrophage",
      "Tahuk"
    ],
    "excludes": "",
    "coords": {
      "xPct": 47.41,
      "yPct": 10.71
    }
  },
  {
    "name": "Cultivation",
    "era": 4,
    "type": "Society",
    "unlocks": [
      "Improvement: Windmill"
    ],
    "effects": [
      "+3 Food on Improvement"
    ],
    "prereq": "",
    "faction": [
      "Aspect",
      "Kin",
      "Lost Lords",
      "Necrophage",
      "Tahuk"
    ],
    "excludes": "Hothouses",
    "coords": {
      "xPct": 56.87,
      "yPct": 4.42
    }
  },
  {
    "name": "Hothouses",
    "era": 4,
    "type": "Society",
    "unlocks": [
      "Improvement: Farming Cooperative"
    ],
    "effects": [
      "-25% Industry cost on Laboratory",
      "-25% Industry cost on Farm"
    ],
    "prereq": "",
    "faction": [
      "Aspect",
      "Kin",
      "Lost Lords",
      "Necrophage",
      "Tahuk"
    ],
    "excludes": "Cultivation",
    "coords": {
      "xPct": 66.31,
      "yPct": 4.42
    }
  },
  {
    "name": "Guilds",
    "era": 4,
    "type": "Economy",
    "unlocks": [
      "Improvement: Workers' League"
    ],
    "effects": [
      "+3 Industry on Improvement"
    ],
    "prereq": "",
    "faction": [
      "Aspect",
      "Kin",
      "Lost Lords",
      "Necrophage",
      "Tahuk"
    ],
    "excludes": "Standardization",
    "coords": {
      "xPct": 68.71,
      "yPct": 26.53
    }
  },
  {
    "name": "Standardization",
    "era": 4,
    "type": "Economy",
    "unlocks": [
      "Improvement: Artisans' Tools"
    ],
    "effects": [
      "-25% Industry cost on Works"
    ],
    "prereq": "",
    "faction": [
      "Aspect",
      "Kin",
      "Lost Lords",
      "Necrophage",
      "Tahuk"
    ],
    "excludes": "Guilds",
    "coords": {
      "xPct": 78.19,
      "yPct": 26.53
    }
  },
  {
    "name": "Banks",
    "era": 4,
    "type": "Economy",
    "unlocks": [
      "Improvement: Thermal Baths",
      "Improvement: Lined Crates"
    ],
    "effects": [
      "+4 Industry on City Hall",
      "+2 Industry on Ministry"
    ],
    "prereq": "",
    "faction": [
      "Aspect",
      "Kin",
      "Lost Lords",
      "Necrophage",
      "Tahuk"
    ],
    "excludes": "",
    "coords": {
      "xPct": 73.45,
      "yPct": 42.42
    }
  },
  {
    "name": "Highway Patrol",
    "era": 4,
    "type": "Economy",
    "unlocks": [
      "Improvement: Scientific Repository",
      "Improvement: Quarry Oversight",
      "Traders' Trails: Paved Roads"
    ],
    "effects": [
      "0.2 Movement Points max to cross a road Tile"
    ],
    "prereq": "",
    "faction": [
      "Aspect",
      "Kin",
      "Lost Lords",
      "Necrophage",
      "Tahuk"
    ],
    "excludes": "",
    "coords": {
      "xPct": 73.4,
      "yPct": 61.3
    }
  },
  {
    "name": "Mercenaries",
    "era": 4,
    "type": "Discovery",
    "unlocks": [
      "Action: Hire Doomwraith Hunter"
    ],
    "effects": [
      "+20% Critical on Unit",
      "-50% Turn cost for Close Rift action"
    ],
    "prereq": "",
    "faction": [
      "Aspect",
      "Kin",
      "Lost Lords",
      "Necrophage",
      "Tahuk"
    ],
    "excludes": "",
    "coords": {
      "xPct": 40.26,
      "yPct": 64.64
    }
  },
  {
    "name": "Digs",
    "era": 4,
    "type": "Discovery",
    "unlocks": [
      "Landscaping Action: Scour"
    ],
    "effects": [
      "-25% Influence cost for Attach Camp action"
    ],
    "prereq": "",
    "faction": [
      "Aspect",
      "Kin",
      "Lost Lords",
      "Necrophage",
      "Tahuk"
    ],
    "excludes": "",
    "coords": {
      "xPct": 47.36,
      "yPct": 77.16
    }
  },
  {
    "name": "Aquadynamics",
    "era": 4,
    "type": "Discovery",
    "unlocks": [
      "Improvement: Fish Farms"
    ],
    "effects": [
      "+25 Precision for season predictability"
    ],
    "prereq": "",
    "faction": [
      "Aspect",
      "Kin",
      "Lost Lords",
      "Necrophage",
      "Tahuk"
    ],
    "excludes": "",
    "coords": {
      "xPct": 54.46,
      "yPct": 64.64
    }
  },
  {
    "name": "Military Engineering",
    "era": 5,
    "type": "Defense",
    "unlocks": [
      "Improvement: Fortified Cities"
    ],
    "effects": [
      "-2 Dust Upkeep on Unit"
    ],
    "prereq": "",
    "faction": [
      "Aspect",
      "Kin",
      "Lost Lords",
      "Necrophage",
      "Tahuk"
    ],
    "excludes": "",
    "coords": {
      "xPct": 30.8,
      "yPct": 32.97
    }
  },
  {
    "name": "Armor Design",
    "era": 5,
    "type": "Defense",
    "unlocks": [
      "Improvement: Protective Carapaces"
    ],
    "effects": [
      "-15% Industry cost on Unit"
    ],
    "prereq": "Military Engineering",
    "faction": [
      "Aspect",
      "Kin",
      "Lost Lords",
      "Necrophage",
      "Tahuk"
    ],
    "excludes": "",
    "coords": {
      "xPct": 18.97,
      "yPct": 20.19
    }
  },
  {
    "name": "The Nurture of Garin",
    "era": 5,
    "type": "Defense",
    "unlocks": [
      "Unit Specialization: Vanguard's Sword"
    ],
    "effects": [
      "+1 Industry on Population"
    ],
    "prereq": "",
    "faction": [
      "Kin"
    ],
    "excludes": "",
    "coords": {
      "xPct": 23.71,
      "yPct": 42.3
    }
  },
  {
    "name": "Elite Focus",
    "era": 5,
    "type": "Defense",
    "unlocks": [
      "Unit Specialization: Bowmaster",
      "Unit Specialization: Executor",
      "Unit Specialization: Commander",
      "Unit Specialization: Champion"
    ],
    "effects": [],
    "prereq": "",
    "faction": [
      "Kin"
    ],
    "excludes": "",
    "coords": {
      "xPct": 23.71,
      "yPct": 61.31
    }
  },
  {
    "name": "Glory of Empire",
    "era": 5,
    "type": "Society",
    "unlocks": [
      "Improvement: Imperial Secretariat"
    ],
    "effects": [
      "+2 Influence on Forums Districts"
    ],
    "prereq": "",
    "faction": [
      "Aspect",
      "Kin",
      "Lost Lords",
      "Necrophage",
      "Tahuk"
    ],
    "excludes": "",
    "coords": {
      "xPct": 37.88,
      "yPct": 20.19
    }
  },
  {
    "name": "Imperial Bureaucracy",
    "era": 5,
    "type": "Society",
    "unlocks": [
      "Improvement: Teahouse"
    ],
    "effects": [
      "+50 Influence on Scribes"
    ],
    "prereq": "Glory of Empire",
    "faction": [
      "Aspect",
      "Kin",
      "Lost Lords",
      "Necrophage",
      "Tahuk"
    ],
    "excludes": "",
    "coords": {
      "xPct": 28.44,
      "yPct": 4.26
    }
  },
  {
    "name": "Preservation",
    "era": 5,
    "type": "Society",
    "unlocks": [
      "Improvement: Canning Shed",
      "Improvement: Nectar Silo"
    ],
    "effects": [
      "+50% Food per Population on Citizens"
    ],
    "prereq": "",
    "faction": [
      "Aspect",
      "Kin",
      "Lost Lords",
      "Necrophage",
      "Tahuk"
    ],
    "excludes": "",
    "coords": {
      "xPct": 56.84,
      "yPct": 20.19
    }
  },
  {
    "name": "Cultural Education",
    "era": 5,
    "type": "Society",
    "unlocks": [
      "Treaty: Shared Victory"
    ],
    "effects": [
      "+400 Influence",
      "+40 Public Opinion on my Empire",
      "+40 Public Opinion on the other Empire"
    ],
    "prereq": "",
    "faction": [
      "Aspect",
      "Kin",
      "Lost Lords",
      "Necrophage",
      "Tahuk"
    ],
    "excludes": "",
    "coords": {
      "xPct": 66.32,
      "yPct": 4.34
    }
  },
  {
    "name": "Large-scale Demolition",
    "era": 5,
    "type": "Economy",
    "unlocks": [
      "Improvement: Ore Breaker",
      "Improvement: Land Clearance",
      "Action: Clear Ridge"
    ],
    "effects": [
      "+50% Industry per Population on Artisans"
    ],
    "prereq": "",
    "faction": [
      "Aspect",
      "Kin",
      "Lost Lords",
      "Necrophage",
      "Tahuk"
    ],
    "excludes": "",
    "coords": {
      "xPct": 73.45,
      "yPct": 23.3
    }
  },
  {
    "name": "Financial Literacy",
    "era": 5,
    "type": "Economy",
    "unlocks": [
      "Improvement: Cashier's Lodge",
      "Improvement: Treasury"
    ],
    "effects": [
      "+25% Dust on Population Vocations"
    ],
    "prereq": "",
    "faction": [
      "Aspect",
      "Kin",
      "Lost Lords",
      "Necrophage",
      "Tahuk"
    ],
    "excludes": "",
    "coords": {
      "xPct": 73.45,
      "yPct": 42.42
    }
  },
  {
    "name": "Tolls and Taxation",
    "era": 5,
    "type": "Economy",
    "unlocks": [
      "Improvement: Customs Inspector"
    ],
    "effects": [
      "+3 Dust on Improvement"
    ],
    "prereq": "",
    "faction": [
      "Aspect",
      "Kin",
      "Lost Lords",
      "Necrophage",
      "Tahuk"
    ],
    "excludes": "Land Management",
    "coords": {
      "xPct": 68.71,
      "yPct": 61.42
    }
  },
  {
    "name": "Land Management",
    "era": 5,
    "type": "Economy",
    "unlocks": [
      "Improvement: Collections Bureau"
    ],
    "effects": [
      "-25% Industry cost on Merchant's House"
    ],
    "prereq": "",
    "faction": [
      "Aspect",
      "Kin",
      "Lost Lords",
      "Necrophage",
      "Tahuk"
    ],
    "excludes": "Tolls and Taxation",
    "coords": {
      "xPct": 78.19,
      "yPct": 61.42
    }
  },
  {
    "name": "University",
    "era": 5,
    "type": "Discovery",
    "unlocks": [
      "Improvement: Lecture Hall"
    ],
    "effects": [
      "+3 Science on Improvement"
    ],
    "prereq": "",
    "faction": [
      "Aspect",
      "Kin",
      "Lost Lords",
      "Necrophage",
      "Tahuk"
    ],
    "excludes": "Inventors' Endowments",
    "coords": {
      "xPct": 30.8,
      "yPct": 80.44
    }
  },
  {
    "name": "Inventors' Endowments",
    "era": 5,
    "type": "Discovery",
    "unlocks": [
      "Improvement: Philosophers' Circle"
    ],
    "effects": [
      "-25% Industry cost on Laboratory"
    ],
    "prereq": "",
    "faction": [
      "Aspect",
      "Kin",
      "Lost Lords",
      "Necrophage",
      "Tahuk"
    ],
    "excludes": "University",
    "coords": {
      "xPct": 40.26,
      "yPct": 80.42
    }
  },
  {
    "name": "Anomanology",
    "era": 5,
    "type": "Discovery",
    "unlocks": [
      "Landscaping Action: Distort (creation of Anomalies)"
    ],
    "effects": [
      "+50% Precision for season predictability",
      "-50% Turn cost on Landscaping Actions"
    ],
    "prereq": "",
    "faction": [
      "Aspect",
      "Kin",
      "Lost Lords",
      "Necrophage",
      "Tahuk"
    ],
    "excludes": "",
    "coords": {
      "xPct": 47.36,
      "yPct": 70.97
    }
  },
  {
    "name": "Scientific Prizes",
    "era": 5,
    "type": "Discovery",
    "unlocks": [
      "Improvement: Grant Treasury",
      "Converter: Citizen Science"
    ],
    "effects": [
      "+2 Science on Laboratories Districts"
    ],
    "prereq": "",
    "faction": [
      "Aspect",
      "Kin",
      "Lost Lords",
      "Necrophage",
      "Tahuk"
    ],
    "excludes": "",
    "coords": {
      "xPct": 54.44,
      "yPct": 64.64
    }
  },
  {
    "name": "Research Institute",
    "era": 5,
    "type": "Discovery",
    "unlocks": [
      "Improvement: Field Studies"
    ],
    "effects": [
      "+50% Science on Scribes"
    ],
    "prereq": "Scientific Prizes",
    "faction": [
      "Aspect",
      "Kin",
      "Lost Lords",
      "Necrophage",
      "Tahuk"
    ],
    "excludes": "",
    "coords": {
      "xPct": 61.56,
      "yPct": 80.42
    }
  },
  {
    "name": "Military Conditioning",
    "era": 6,
    "type": "Defense",
    "unlocks": [],
    "effects": [
      "+50 Health on Unit",
      "-50% Dust Upkeep on Unit",
      "+5 Minimal Damage on Unit",
      "+10 Maximum Damage on Unit",
      "+10 Defense on Unit"
    ],
    "prereq": "",
    "faction": [
      "Aspect",
      "Kin",
      "Lost Lords",
      "Necrophage",
      "Tahuk"
    ],
    "excludes": "",
    "coords": {
      "xPct": 27.06,
      "yPct": 45.0
    }
  },
  {
    "name": "Mass Psychology",
    "era": 6,
    "type": "Society",
    "unlocks": [],
    "effects": [
      "+20 Approval on City Hall",
      "+15% Influence on City Hall"
    ],
    "prereq": "",
    "faction": [
      "Aspect",
      "Kin",
      "Lost Lords",
      "Necrophage",
      "Tahuk"
    ],
    "excludes": "",
    "coords": {
      "xPct": 41.63,
      "yPct": 11.75
    }
  },
  {
    "name": "Civilization Optimizations",
    "era": 6,
    "type": "Society",
    "unlocks": [],
    "effects": [
      "+1 Industry on Population per Jubilant City",
      "+1 Dust on Population per Jubilant City",
      "+1 Science on Population per Jubilant City",
      "+1 Influence on Population per Jubilant City",
      "-50% cost to grow all Populations"
    ],
    "prereq": "",
    "faction": [
      "Aspect",
      "Kin",
      "Lost Lords",
      "Necrophage",
      "Tahuk"
    ],
    "excludes": "",
    "coords": {
      "xPct": 51.51,
      "yPct": 11.63
    }
  },
  {
    "name": "Stock Exchange",
    "era": 6,
    "type": "Economy",
    "unlocks": [],
    "effects": [
      "+100% Food on District",
      "+100% Industry on District",
      "+100% Influence on District",
      "+100% Dust on District",
      "+100% Science on District",
      "-50% Influence cost on Foundation"
    ],
    "prereq": "",
    "faction": [
      "Aspect",
      "Kin",
      "Lost Lords",
      "Necrophage",
      "Tahuk"
    ],
    "excludes": "",
    "coords": {
      "xPct": 66.63,
      "yPct": 29.5
    }
  },
  {
    "name": "Dust Seismology",
    "era": 6,
    "type": "Economy",
    "unlocks": [],
    "effects": [
      "+15% Dust on City Hall",
      "-50% Buyout cost on Unit",
      "-50% Buyout cost on District",
      "-50% Buyout cost on Improvement"
    ],
    "prereq": "",
    "faction": [
      "Aspect",
      "Kin",
      "Lost Lords",
      "Necrophage",
      "Tahuk"
    ],
    "excludes": "",
    "coords": {
      "xPct": 67.15,
      "yPct": 56.23
    }
  },
  {
    "name": "Arcana of the Ancients",
    "era": 6,
    "type": "Discovery",
    "unlocks": [],
    "effects": [
      "+15% Science on City Hall",
      "-20% on all Technology research cost"
    ],
    "prereq": "",
    "faction": [
      "Aspect",
      "Kin",
      "Lost Lords",
      "Necrophage",
      "Tahuk"
    ],
    "excludes": "",
    "coords": {
      "xPct": 47.4,
      "yPct": 73.83
    }
  }
]
